<annotation>
	<folder>training</folder>
	<filename>bredelehackathon_58_of_511.jpeg</filename>
	<path>/Users/Dotnetmobile/Documents/bredele-hackathon/images-small/training/bredelehackathon_58_of_511.jpeg</path>
	<source>
		<database>Unknown</database>
	</source>
	<size>
		<width>756</width>
		<height>1008</height>
		<depth>3</depth>
	</size>
	<segmented>0</segmented>
	<object>
		<name>king mage</name>
		<pose>Unspecified</pose>
		<truncated>1</truncated>
		<difficult>0</difficult>
		<bndbox>
			<xmin>302</xmin>
			<ymin>463</ymin>
			<xmax>752</xmax>
			<ymax>1008</ymax>
		</bndbox>
	</object>
	<object>
		<name>santa claus</name>
		<pose>Unspecified</pose>
		<truncated>1</truncated>
		<difficult>0</difficult>
		<bndbox>
			<xmin>5</xmin>
			<ymin>1</ymin>
			<xmax>377</xmax>
			<ymax>576</ymax>
		</bndbox>
	</object>
	<object>
		<name>angel</name>
		<pose>Unspecified</pose>
		<truncated>1</truncated>
		<difficult>0</difficult>
		<bndbox>
			<xmin>1</xmin>
			<ymin>568</ymin>
			<xmax>224</xmax>
			<ymax>1004</ymax>
		</bndbox>
	</object>
</annotation>
