<annotation>
	<folder>training</folder>
	<filename>bredelehackathon_296_of_511.jpeg</filename>
	<path>/Users/Dotnetmobile/Documents/bredele-hackathon/images-small/training/bredelehackathon_296_of_511.jpeg</path>
	<source>
		<database>Unknown</database>
	</source>
	<size>
		<width>756</width>
		<height>1008</height>
		<depth>3</depth>
	</size>
	<segmented>0</segmented>
	<object>
		<name>snowball</name>
		<pose>Unspecified</pose>
		<truncated>0</truncated>
		<difficult>0</difficult>
		<bndbox>
			<xmin>77</xmin>
			<ymin>94</ymin>
			<xmax>502</xmax>
			<ymax>509</ymax>
		</bndbox>
	</object>
	<object>
		<name>snowball</name>
		<pose>Unspecified</pose>
		<truncated>1</truncated>
		<difficult>0</difficult>
		<bndbox>
			<xmin>630</xmin>
			<ymin>289</ymin>
			<xmax>756</xmax>
			<ymax>584</ymax>
		</bndbox>
	</object>
	<object>
		<name>snowball</name>
		<pose>Unspecified</pose>
		<truncated>0</truncated>
		<difficult>0</difficult>
		<bndbox>
			<xmin>248</xmin>
			<ymin>582</ymin>
			<xmax>552</xmax>
			<ymax>935</ymax>
		</bndbox>
	</object>
	<object>
		<name>snowball</name>
		<pose>Unspecified</pose>
		<truncated>1</truncated>
		<difficult>0</difficult>
		<bndbox>
			<xmin>564</xmin>
			<ymin>745</ymin>
			<xmax>756</xmax>
			<ymax>995</ymax>
		</bndbox>
	</object>
</annotation>
